NginxCongRumenDaoJingtongPdfXiazaiTtlsaChupin/README.md
NginxCongRumenDaoJingtongPdfXiazaiTtlsaChupin/__init__.py
NginxCongRumenDaoJingtongPdfXiazaiTtlsaChupin/__main__.py
NginxCongRumenDaoJingtongPdfXiazaiTtlsaChupin/file.pdf
NginxCongRumenDaoJingtongPdfXiazaiTtlsaChupin/index.html
nginx_cong_rumen_dao_jingtong_pdf_xiazai_ttlsa_chupin-2024.3.1.0.dist-info/METADATA
nginx_cong_rumen_dao_jingtong_pdf_xiazai_ttlsa_chupin-2024.3.1.0.dist-info/WHEEL
nginx_cong_rumen_dao_jingtong_pdf_xiazai_ttlsa_chupin-2024.3.1.0.dist-info/entry_points.txt
nginx_cong_rumen_dao_jingtong_pdf_xiazai_ttlsa_chupin-2024.3.1.0.dist-info/top_level.txt
nginx_cong_rumen_dao_jingtong_pdf_xiazai_ttlsa_chupin-2024.3.1.0.dist-info/RECORD
